contextocracker/__init__.py
contextocracker/collect_scores.py
contextocracker/data_collection_async.py
contextocracker/exceptions.py
contextocracker/phase0/__init__.py
contextocracker/phase0/filter_words.py
contextocracker/resources/__init__.py
contextocracker/resources/brown_and_word_list.txt
contextocracker/resources/brown_words_filtered.txt
contextocracker/resources/words_alpha_filtered.txt
contextocracker-0.0.1.dist-info/METADATA
contextocracker-0.0.1.dist-info/WHEEL
contextocracker-0.0.1.dist-info/RECORD
